winpwn/__init__.py
winpwn/context.py
winpwn/dbg.py
winpwn/misc.py
winpwn/var.py
winpwn/win.py
winpwn/winpwn.py
repwn-0.0.1.dist-info/METADATA
repwn-0.0.1.dist-info/WHEEL
repwn-0.0.1.dist-info/top_level.txt
repwn-0.0.1.dist-info/RECORD
